{
  "version": "1.97.1",
  "description": "Visual Studio Code",
  "homepage": "https://code.visualstudio.com/",
  "license": "MIT",
  "architecture": {
    "64bit": {
      "url": "https://update.code.visualstudio.com/1.97.1/win32-x64-user/stable#/VSCodeUserSetup.exe",
      "hash": "sha256:8d0742a4c993e384fde4e802f8684ebbfdcfb13891e191e7a6da94eb1574e52e",
      "shortcuts": [
        [
          "VSCodeUserSetup.exe",
          "Install VSCode(x64)"
        ]
      ],
      "post_install": [
        "&\"$dir\\VSCodeUserSetup.exe\""
      ]
    },
    "arm64": {
      "url": "https://update.code.visualstudio.com/1.97.1/win32-arm64-user/stable#/VSCodeUserSetup.exe",
      "hash": "sha256:375ba3db6c9ef1b9762f43aeebb1626970db59b5b71e512fe7aec3decaba59a2",
      "shortcuts": [
        [
          "VSCodeUserSetup.exe",
          "Install VSCode(arm64)"
        ]
      ],
      "post_install": [
        "&\"$dir\\VSCodeUserSetup.exe\""
      ]
    }
  }
}